carbon_intensity_mcp/__init__.py
carbon_intensity_mcp/models.py
carbon_intensity_mcp/server.py
carbon_intensity_mcp-0.1.1.dist-info/METADATA
carbon_intensity_mcp-0.1.1.dist-info/WHEEL
carbon_intensity_mcp-0.1.1.dist-info/entry_points.txt
carbon_intensity_mcp-0.1.1.dist-info/RECORD
