Metadata-Version: 2.4
Name: carbon-intensity-mcp
Version: 0.1.1
Summary: MCP server for UK Carbon Intensity API
Author-email: benomahony <ben@benomahony.com>
Requires-Python: >=3.12
Requires-Dist: httpx>=0.27.0
Requires-Dist: mcp>=1.1.0
Requires-Dist: pydantic>=2.0.0
